{"users":[{"subject":"aborer","permission":"Owner"},{"subject":"sjacobi","permission":"Owner"},{"subject":"aemard","permission":"Owner"},{"subject":"bkuvalis","permission":"Owner"},{"subject":"xking","permission":"Owner"},{"subject":"kkrajcik","permission":"Owner"},{"subject":"dlynch","permission":"Owner"},{"subject":"dcarter","permission":"Owner"},{"subject":"hmaggio","permission":"Owner"},{"subject":"wlebsack","permission":"Owner"},{"subject":"aschulist","permission":"Owner"},{"subject":"cdamore","permission":"Owner"},{"subject":"lledner","permission":"Owner"},{"subject":"zdouglas","permission":"Owner"},{"subject":"afritsch","permission":"Owner"},{"subject":"srunolfsson","permission":"Owner"},{"subject":"hleannon","permission":"Owner"},{"subject":"slowe","permission":"Owner"},{"subject":"mdamore","permission":"Owner"},{"subject":"blesch","permission":"Owner"},{"subject":"fkerluke","permission":"Owner"},{"subject":"rdickens","permission":"Owner"},{"subject":"aheller","permission":"Editor"},{"subject":"sdaniel","permission":"Owner"},{"subject":"aschaefer","permission":"Owner"},{"subject":"aking","permission":"Viewer"},{"subject":"dnicolas","permission":"Owner"},{"subject":"mjakubowski","permission":"Owner"},{"subject":"jnikolaus","permission":"Owner"},{"subject":"prunolfsson","permission":"Owner"},{"subject":"bhagenes","permission":"Editor"},{"subject":"hwill","permission":"Owner"},{"subject":"jgottlieb","permission":"Owner"},{"subject":"swyman","permission":"Owner"},{"subject":"rstoltenberg","permission":"Owner"},{"subject":"knikolaus","permission":"Owner"},{"subject":"mreilly","permission":"Owner"},{"subject":"bbeer","permission":"Owner"},{"subject":"fwalsh","permission":"Owner"},{"subject":"tparisian","permission":"Owner"},{"subject":"afahey","permission":"Full"},{"subject":"ckilback","permission":"Owner"},{"subject":"kortiz","permission":"Owner"},{"subject":"browe","permission":"Owner"},{"subject":"rpfannerstill","permission":"Owner"},{"subject":"jhamill","permission":"Owner"},{"subject":"rhoeger","permission":"Owner"},{"subject":"nheller","permission":"Owner"},{"subject":"mkonopelski","permission":"Owner"},{"subject":"dlegros","permission":"Owner"},{"subject":"scorkery","permission":"Owner"},{"subject":"rvandervort","permission":"Owner"},{"subject":"bstrosin","permission":"Owner"},{"subject":"dfisher","permission":"Owner"},{"subject":"blubowitz","permission":"Owner"},{"subject":"dlang","permission":"Owner"},{"subject":"kkunde","permission":"Owner"},{"subject":"lkohler","permission":"Owner"},{"subject":"aortiz","permission":"Owner"},{"subject":"david","permission":"Owner"},{"subject":"dcrooks","permission":"Owner"},{"subject":"agraham","permission":"Owner"},{"subject":"cdaniel","permission":"Owner"},{"subject":"jlehner","permission":"Owner"},{"subject":"jkoss","permission":"Owner"},{"subject":"ebruen","permission":"Owner"}],"groups":[{"subject":"Apples","permission":"Editor"},{"subject":"Bananas","permission":"Editor"}]}